dockery-0.8.1.dist-info/METADATA
dockery-0.8.1.dist-info/WHEEL
dockery-0.8.1.dist-info/entry_points.txt
dockery-0.8.1.dist-info/licenses/LICENSE
dockery/__init__.py
dockery/containers.py
dockery/custom_widgets.py
dockery/gui.py
dockery/images.py
dockery/logs.py
dockery/main.py
dockery/models.py
dockery/networks.py
dockery/style.css
dockery/utils.py
dockery/volumes.py
dockery-0.8.1.dist-info/RECORD
