Metadata-Version: 2.1
Name: dockery
Version: 0.8.1
Summary: Graphical interface for Docker in your console
Author-Email: Mariano Carrazana <marianocarrazana@gmail.com>
License: MIT
Project-URL: Bug tracker, https://github.com/marianocarrazana/dockery/issues
Project-URL: Source code, https://github.com/marianocarrazana/dockery
Requires-Python: >=3.9
Requires-Dist: docker>=6.1.3
Requires-Dist: textual==0.35.1
Requires-Dist: click>=8.1.3
Requires-Dist: pyyaml>=6.0
